assignment8/gray.v
module gray_counter (
    input clk,
    input rst,
    output reg [3:0] q
);

always @(posedge clk or posedge rst) begin
    if (rst) begin
        q <= 4'b0000;
    end else begin
        case (q)
            4'b0000: q <= 4'b0001;
            4'b0001: q <= 4'b0011;
            4'b0011: q <= 4'b0010;
            4'b0010: q <= 4'b0110;
            4'b0110: q <= 4'b0111;
            4'b0111: q <= 4'b0101;
            4'b0101: q <= 4'b0100;
            4'b0100: q <= 4'b1100;
            4'b1100: q <= 4'b1101;
            4'b1101: q <= 4'b1111;
            4'b1111: q <= 4'b1110;
            4'b1110: q <= 4'b1010;
            4'b1010: q <= 4'b1011;
            4'b1011: q <= 4'b1001;
            4'b1001: q <= 4'b1000;
            4'b1000: q <= 4'b0000; // count completion → reset
            default: q <= 4'b0000;
        endcase
    end
end

endmodule

`timescale 1ns/1ps

module gray_counter_tb;

reg clk;
reg rst;
wire [3:0] q;

// Instantiate DUT (Device Under Test)
gray_counter uut (
    .clk(clk),
    .rst(rst),
    .q(q)
);

// Clock generation (10 ns period)
always #5 clk = ~clk;

initial begin
    // Initialize
    clk = 0;
    rst = 1;

    // Dump file setup
    $dumpfile("gray.vcd");
    $dumpvars(0, gray_counter_tb);

    // Apply reset
    #10 rst = 0;

    // Let counter run for a while
    #200;

    // Apply reset again to check behavior
    rst = 1;
    #10 rst = 0;

    #100;

    $finish;
end

endmodule

assignment8/gray.vcd
$date
	Tue Apr  7 23:38:49 2026
$end
$version
	Icarus Verilog
$end
$timescale
	1ps
$end
$scope module gray_counter_tb $end
$var wire 4 ! q [3:0] $end
$var reg 1 " clk $end
$var reg 1 # rst $end
$scope module uut $end
$var wire 1 " clk $end
$var wire 1 # rst $end
$var reg 4 $ q [3:0] $end
$upscope $end
$upscope $end
$enddefinitions $end
$comment Show the parameter values. $end
$dumpall
$end
#0
$dumpvars
b0 $
1#
0"
b0 !
$end
#5000
1"
#10000
0"
0#
#15000
b1 !
b1 $
1"
#20000
0"
#25000
b11 !
b11 $
1"
#30000
0"
#35000
b10 !
b10 $
1"
#40000
0"
#45000
b110 !
b110 $
1"
#50000
0"
#55000
b111 !
b111 $
1"
#60000
0"
#65000
b101 !
b101 $
1"
#70000
0"
#75000
b100 !
b100 $
1"
#80000
0"
#85000
b1100 !
b1100 $
1"
#90000
0"
#95000
b1101 !
b1101 $
1"
#100000
0"
#105000
b1111 !
b1111 $
1"
#110000
0"
#115000
b1110 !
b1110 $
1"
#120000
0"
#125000
b1010 !
b1010 $
1"
#130000
0"
#135000
b1011 !
b1011 $
1"
#140000
0"
#145000
b1001 !
b1001 $
1"
#150000
0"
#155000
b1000 !
b1000 $
1"
#160000
0"
#165000
b0 !
b0 $
1"
#170000
0"
#175000
b1 !
b1 $
1"
#180000
0"
#185000
b11 !
b11 $
1"
#190000
0"
#195000
b10 !
b10 $
1"
#200000
0"
#205000
b110 !
b110 $
1"
#210000
b0 !
b0 $
0"
1#
#215000
1"
#220000
0"
0#
#225000
b1 !
b1 $
1"
#230000
0"
#235000
b11 !
b11 $
1"
#240000
0"
#245000
b10 !
b10 $
1"
#250000
0"
#255000
b110 !
b110 $
1"
#260000
0"
#265000
b111 !
b111 $
1"
#270000
0"
#275000
b101 !
b101 $
1"
#280000
0"
#285000
b100 !
b100 $
1"
#290000
0"
#295000
b1100 !
b1100 $
1"
#300000
0"
#305000
b1101 !
b1101 $
1"
#310000
0"
#315000
b1111 !
b1111 $
1"
