assignment8/johnsoncount.v
`timescale 1ns/1ns
module johnsoncount(output [3:0] y,input clk,rst);
reg [3:0] c;
reg temp;
initial begin
    c = 4'b0000;
end
always @(posedge clk) begin
    if(rst) c=4'b0;
    else begin 
        temp = ~c[0];
        c = c>>1;
        c[3] = temp;
    end
end
assign y = c;
endmodule

module tb;
reg clock,rst;
wire [3:0] x;

// assign clock=0;
initial begin 
clock = 1'b0;
rst = 0;
end
always #2 clock <= ~clock;
johnsoncount c1 (x, clock, rst);
initial begin
    $monitor("Time = %0t | rst=%b COUNT=%b", $time, rst, x);
    #110 rst = 1;
    #7 rst = 0;
end
initial begin
    
    $dumpfile("johnsoncount.vcd");
    $dumpvars;
    #150 $finish;
end

endmodule

assignment8/johnsoncount.vcd
$date
	Sat Apr 04 18:50:17 2026
$end
$version
	Icarus Verilog
$end
$timescale
	1ns
$end
$scope module tb $end
$var wire 4 ! x [3:0] $end
$var reg 1 " clock $end
$var reg 1 # rst $end
$scope module c1 $end
$var wire 1 " clk $end
$var wire 1 # rst $end
$var wire 4 $ y [3:0] $end
$var reg 4 % c [3:0] $end
$var reg 1 & temp $end
$upscope $end
$upscope $end
$enddefinitions $end
$comment Show the parameter values. $end
$dumpall
$end
#0
$dumpvars
x&
b0 %
b0 $
0#
0"
b0 !
$end
#2
b1000 !
b1000 $
b1000 %
1&
1"
#4
0"
#6
b1100 !
b1100 $
b1100 %
1"
#8
0"
#10
b1110 !
b1110 $
b1110 %
1"
#12
0"
#14
b1111 !
b1111 $
b1111 %
1"
#16
0"
#18
b111 !
b111 $
b111 %
0&
1"
#20
0"
#22
b11 !
b11 $
b11 %
1"
#24
0"
#26
b1 !
b1 $
b1 %
1"
#28
0"
#30
b0 !
b0 $
b0 %
1"
#32
0"
#34
b1000 !
b1000 $
b1000 %
1&
1"
#36
0"
#38
b1100 !
b1100 $
b1100 %
1"
#40
0"
#42
b1110 !
b1110 $
b1110 %
1"
#44
0"
#46
b1111 !
b1111 $
b1111 %
1"
#48
0"
#50
b111 !
b111 $
b111 %
0&
1"
#52
0"
#54
b11 !
b11 $
b11 %
1"
#56
0"
#58
b1 !
b1 $
b1 %
1"
#60
0"
#62
b0 !
b0 $
b0 %
1"
#64
0"
#66
b1000 !
b1000 $
b1000 %
1&
1"
#68
0"
#70
b1100 !
b1100 $
b1100 %
1"
#72
0"
#74
b1110 !
b1110 $
b1110 %
1"
#76
0"
#78
b1111 !
b1111 $
b1111 %
1"
#80
0"
#82
b111 !
b111 $
b111 %
0&
1"
#84
0"
#86
b11 !
b11 $
b11 %
1"
#88
0"
#90
b1 !
b1 $
b1 %
1"
#92
0"
#94
b0 !
b0 $
b0 %
1"
#96
0"
#98
b1000 !
b1000 $
b1000 %
1&
1"
#100
0"
#102
b1100 !
b1100 $
b1100 %
1"
#104
0"
#106
b1110 !
b1110 $
b1110 %
1"
#108
0"
#110
b0 !
b0 $
b0 %
1"
1#
#112
0"
#114
1"
#116
0"
#117
0#
#118
b1000 !
b1000 $
b1000 %
1"
#120
0"
#122
b1100 !
b1100 $
b1100 %
1"
#124
0"
#126
b1110 !
b1110 $
b1110 %
1"
#128
0"
#130
b1111 !
b1111 $
b1111 %
1"
#132
0"
#134
b111 !
b111 $
b111 %
0&
1"
#136
0"
#138
b11 !
b11 $
b11 %
1"
#140
0"
#142
b1 !
b1 $
b1 %
1"
#144
0"
#146
b0 !
b0 $
b0 %
1"
#148
0"
#150
b1000 !
b1000 $
b1000 %
1&
1"
