assignment8/mod10counter.v
`timescale 1ns/1ps
module mod10counter (
    input clk, rst, output [3:0] count
);
reg [3:0] c;
initial begin
    c = 4'b0;
end
always @(posedge clk) begin
    if(rst) c=4'b0;
    else c=c+1;
    if(c>9) c= 0;
end
assign count = c;

endmodule

module tb;
reg clock,rst;
wire [3:0] cnt;

// assign clock=0;
initial begin 
clock = 1'b0;
rst = 0;
end
always #5 clock <= ~clock;
mod10counter c1 (clock, rst, cnt);
initial begin
    $monitor("Time = %0t | rst=%b COUNT=%d", $time, rst, cnt);
    #110 rst = 1;
    #7 rst = 0;
end
initial begin
    
    $dumpfile("mod10counter.vcd");
    $dumpvars;
    #150 $finish;
end

endmodule

assignment8/mod10counter.vcd
$date
	Sat Apr 04 18:08:37 2026
$end
$version
	Icarus Verilog
$end
$timescale
	1ps
$end
$scope module tb $end
$var wire 4 ! cnt [3:0] $end
$var reg 1 " clock $end
$var reg 1 # rst $end
$scope module c1 $end
$var wire 1 " clk $end
$var wire 4 $ count [3:0] $end
$var wire 1 # rst $end
$var reg 4 % c [3:0] $end
$upscope $end
$upscope $end
$enddefinitions $end
$comment Show the parameter values. $end
$dumpall
$end
#0
$dumpvars
b0 %
b0 $
0#
0"
b0 !
$end
#5000
b1 !
b1 $
b1 %
1"
#10000
0"
#15000
b10 !
b10 $
b10 %
1"
#20000
0"
#25000
b11 !
b11 $
b11 %
1"
#30000
0"
#35000
b100 !
b100 $
b100 %
1"
#40000
0"
#45000
b101 !
b101 $
b101 %
1"
#50000
0"
#55000
b110 !
b110 $
b110 %
1"
#60000
0"
#65000
b111 !
b111 $
b111 %
1"
#70000
0"
#75000
b1000 !
b1000 $
b1000 %
1"
#80000
0"
#85000
b1001 !
b1001 $
b1001 %
1"
#90000
0"
#95000
b0 !
b0 $
b0 %
1"
#100000
0"
#105000
b1 !
b1 $
b1 %
1"
#110000
0"
1#
#115000
b0 !
b0 $
b0 %
1"
#117000
0#
#120000
0"
#125000
b1 !
b1 $
b1 %
1"
#130000
0"
#135000
b10 !
b10 $
b10 %
1"
#140000
0"
#145000
b11 !
b11 $
b11 %
1"
