assignment8/ring_4bitcount.v
`timescale 1ns/1ps
module ring_4bitcount(output [3:0] y,input clk,rst);
reg [3:0] c;
initial begin
    c = 4'b0001;
end
always @(posedge clk) begin
    if(rst) c=4'b0001;
    else c = c<<1;
    if(c==0) c= 0001;
end
assign y = c;
endmodule

module tb;
reg clock,rst;
wire [3:0] x;

// assign clock=0;
initial begin 
clock = 1'b0;
rst = 0;
end
always #5 clock <= ~clock;
ring_4bitcount c1 (x, clock, rst);
initial begin
    $monitor("Time = %0t | rst=%b COUNT=%b", $time, rst, x);
    #110 rst = 1;
    #7 rst = 0;
end
initial begin
    
    $dumpfile("ringcount.vcd");
    $dumpvars;
    #150 $finish;
end

endmodule

assignment8/ringcount.vcd
$date
	Sat Apr 04 18:35:48 2026
$end
$version
	Icarus Verilog
$end
$timescale
	1s
$end
$scope module tb $end
$var wire 4 ! x [3:0] $end
$var reg 1 " clock $end
$var reg 1 # rst $end
$scope module c1 $end
$var wire 1 " clk $end
$var wire 1 # rst $end
$var wire 4 $ y [3:0] $end
$var reg 4 % c [3:0] $end
$upscope $end
$upscope $end
$enddefinitions $end
$comment Show the parameter values. $end
$dumpall
$end
#0
$dumpvars
b1 %
b1 $
0#
0"
b1 !
$end
#5
b10 !
b10 $
b10 %
1"
#10
0"
#15
b100 !
b100 $
b100 %
1"
#20
0"
#25
b1000 !
b1000 $
b1000 %
1"
#30
0"
#35
b1 !
b1 $
b1 %
1"
#40
0"
#45
b10 !
b10 $
b10 %
1"
#50
0"
#55
b100 !
b100 $
b100 %
1"
#60
0"
#65
b1000 !
b1000 $
b1000 %
1"
#70
0"
#75
b1 !
b1 $
b1 %
1"
#80
0"
#85
b10 !
b10 $
b10 %
1"
#90
0"
#95
b100 !
b100 $
b100 %
1"
#100
0"
#105
b1000 !
b1000 $
b1000 %
1"
#110
0"
1#
#115
b1 !
b1 $
b1 %
1"
#117
0#
#120
0"
#125
b10 !
b10 $
b10 %
1"
#130
0"
#135
b100 !
b100 $
b100 %
1"
#140
0"
#145
b1000 !
b1000 $
b1000 %
1"
