assignment8/updowncount.v
`timescale 1ns/1ps
module updowncount (
    input clk, rst,m, output [3:0] count
);
reg [3:0] c;
initial begin
    c <= 4'b0;
end
always @(posedge clk) begin
    if(rst) c=4'b0;
    else if(m==1) c<=c+1;
    else if(m==0) c<=c-1;
    
end
assign count = c;

endmodule

module tb;
reg clock,rst,mo;
wire [3:0] cnt;

// assign clock=0;
initial begin 
clock <= 1'b0;
rst <= 0;
mo <= 0;
end
always #5 clock <= ~clock;
updowncount c1 (clock, rst, mo,cnt);
initial begin
    $monitor("Time = %0t | rst=%b COUNT=%d | Mode =%b", $time, rst, cnt,mo);
    #50 mo <= 1;
    #10 mo <= 0;
    #110 rst <= 1;
    #7 rst <= 0;
end
initial begin
    
    $dumpfile("updown.vcd");
    $dumpvars;
    #250 $finish;
end

endmodule

assignment8/updown.vcd
$date
	Sat Apr 04 19:03:18 2026
$end
$version
	Icarus Verilog
$end
$timescale
	1ps
$end
$scope module tb $end
$var wire 4 ! cnt [3:0] $end
$var reg 1 " clock $end
$var reg 1 # mo $end
$var reg 1 $ rst $end
$scope module c1 $end
$var wire 1 " clk $end
$var wire 4 % count [3:0] $end
$var wire 1 # m $end
$var wire 1 $ rst $end
$var reg 4 & c [3:0] $end
$upscope $end
$upscope $end
$enddefinitions $end
$comment Show the parameter values. $end
$dumpall
$end
#0
$dumpvars
b0 &
b0 %
0$
0#
0"
b0 !
$end
#5000
b1111 !
b1111 %
b1111 &
1"
#10000
0"
#15000
b1110 !
b1110 %
b1110 &
1"
#20000
0"
#25000
b1101 !
b1101 %
b1101 &
1"
#30000
0"
#35000
b1100 !
b1100 %
b1100 &
1"
#40000
0"
#45000
b1011 !
b1011 %
b1011 &
1"
#50000
0"
1#
#55000
b1100 !
b1100 %
b1100 &
1"
#60000
0"
0#
#65000
b1011 !
b1011 %
b1011 &
1"
#70000
0"
#75000
b1010 !
b1010 %
b1010 &
1"
#80000
0"
#85000
b1001 !
b1001 %
b1001 &
1"
#90000
0"
#95000
b1000 !
b1000 %
b1000 &
1"
#100000
0"
#105000
b111 !
b111 %
b111 &
1"
#110000
0"
#115000
b110 !
b110 %
b110 &
1"
#120000
0"
#125000
b101 !
b101 %
b101 &
1"
#130000
0"
#135000
b100 !
b100 %
b100 &
1"
#140000
0"
#145000
b11 !
b11 %
b11 &
1"
#150000
0"
#155000
b10 !
b10 %
b10 &
1"
#160000
0"
#165000
b1 !
b1 %
b1 &
1"
#170000
0"
1$
#175000
b0 !
b0 %
b0 &
1"
#177000
0$
#180000
0"
#185000
b1111 !
b1111 %
b1111 &
1"
#190000
0"
#195000
b1110 !
b1110 %
b1110 &
1"
#200000
0"
#205000
b1101 !
b1101 %
b1101 &
1"
#210000
0"
#215000
b1100 !
b1100 %
b1100 &
1"
#220000
0"
#225000
b1011 !
b1011 %
b1011 &
1"
#230000
0"
#235000
b1010 !
b1010 %
b1010 &
1"
#240000
0"
#245000
b1001 !
b1001 %
b1001 &
1"
